TheToolsBox/__init__.py
TheToolsBox/baseLib.py
metaCore/__init__.py
metaCore/baseLib.py
TheToolsBox-1.0.9.dist-info/METADATA
TheToolsBox-1.0.9.dist-info/WHEEL
TheToolsBox-1.0.9.dist-info/top_level.txt
TheToolsBox-1.0.9.dist-info/RECORD
