Metadata-Version: 2.1
Name: TheToolsBox
Version: 1.0.9
Summary: Description de ma librairie
Home-page: https://github.com/VectraNoxCorp/TheToolsBox
Author: Vectra
Author-email: Jarvis.noxingcorporation@gmail.com
Classifier: Programming Language :: Python :: 3
Classifier: License :: OSI Approved :: MIT License
Classifier: Operating System :: OS Independent
Requires-Python: >=3.6
Requires-Dist: python-docx
Requires-Dist: openpyxl
Requires-Dist: gtts
Requires-Dist: requests
Requires-Dist: psutil
